NHXDB/NHXDB.py
NHXDB/__init__.py
NHXDB-1.3.2.dist-info/LICENSE
NHXDB-1.3.2.dist-info/METADATA
NHXDB-1.3.2.dist-info/WHEEL
NHXDB-1.3.2.dist-info/top_level.txt
NHXDB-1.3.2.dist-info/RECORD
