Metadata-Version: 2.1
Name: NHXDB
Version: 1.3.2
Summary: A lightweight Database Module with a blend of SQL-like Language and ORM syntax
Home-page: https://github.com/NHXTech/NHXDB
Author: NHXTech
Author-email: chmuhammadsohaib@gmail.com
License: MIT
Keywords: NHXDB NHXTech chmuhammadsohaib NHX Database DBMS
Platform: UNKNOWN
Classifier: Development Status :: 5 - Production/Stable
Classifier: Intended Audience :: Developers
Classifier: Topic :: Software Development :: Build Tools
Classifier: Programming Language :: Python :: 3
Classifier: License :: OSI Approved :: MIT License
Classifier: Operating System :: OS Independent
Requires-Python: >=3
